Workbook

Sheet Read me
A1: Golden household: example spreadsheet (Phase 45.1)
A3: An example of how the expected figures can be worked out, not the answers. It shows the layout; the figures are yours.
A4: Per #393 your spreadsheet must be worked out from the inputs and spec.md alone. The few formulas filled in here were written by Claude
A5: to show the pattern; they share Claude's reading of the spec, so check each against the spec (or rewrite it) before you trust it.
A7: Legend
A8: Blue text: inputs, pasted from tests/Fixtures/golden/inputs/*.csv. Don't edit; rebuild the tabs if the CSVs change.
A9: Green text: a formula that links to another sheet.
A10: Black text: a formula on the same sheet, or a label.
A11: Yellow fill: yours to fill in (the expected tab, and the finance lines at the foot of the Ledger).
A13: Tabs
A14: expected: the 890 figures. Each row says how its figure is filled: an example formula, or "yours".
A15: Reports: spend per vehicle, year and group, from the Ledger (worked example).
... A28: When done: save the expected tab alone as CSV (UTF-8), keeping its header, over tests/Fixtures/golden/expected.csv.

Sheet users
A1: user | B1: display_name | C1: locale | D1: timezone | E1: currency | F1: distance_unit | G1: volume_unit | H1: tax_year_start | I1: is_admin
A2: alex | B2: Alex | C2: en_GB | D2: Europe/London | E2: GBP | F2: mi | G2: l | H2: 04-06 | I2: yes
A3: sam | B3: Sam | C3: en_IE | D3: Europe/Dublin | E3: EUR | F3: km | G3: l | H3: 01-01 | I3: no

Sheet Reports
A1: Reports: spend per vehicle, calendar year and group (worked example)
A2: SUMIFS over the Ledger. Finance lines count only once you add them on the Ledger sheet.
A4: vehicle | B4: year | C4: fuel | D4: maintenance | E4: compliance | F4: other | G4: total
A5: golf | B5: 2023 | C5: =SUMIFS(Ledger!$E$2:$E$846,Ledger!$A$2:$A$846,$A5,Ledger!$F$2:$F$846,$B5,Ledger!$C$2:$C$846,C$4) | D5: =SUMIFS(Ledger!$E$2:$E$846,Ledger!$A$2:$A$846,$A5,Ledger!$F$2:$F$846,$B5,Ledger!$C$2:$C$846,D$4) | E5: =SUMIFS(Ledger!$E$2:$E$846,Ledger!$A$2:$A$846,$A5,Ledger!$F$2:$F$846,$B5,Ledger!$C$2:$C$846,E$4) | F5: =SUMIFS(Ledger!$E$2:$E$846,Ledger!$A$2:$A$846,$A5,Ledger!$F$2:$F$846,$B5,Ledger!$C$2:$C$846,F$4) | G5: =SUM(C5:F5)
A6: golf | B6: 2024 | C6: =SUMIFS(Ledger!$E$2:$E$846,Ledger!$A$2:$A$846,$A6,Ledger!$F$2:$F$846,$B6,Ledger!$C$2:$C$846,C$4) | D6: =SUMIFS(Ledger!$E$2:$E$846,Ledger!$A$2:$A$846,$A6,Ledger!$F$2:$F$846,$B6,Ledger!$C$2:$C$846,D$4) | E6: =SUMIFS(Ledger!$E$2:$E$846,Ledger!$A$2:$A$846,$A6,Ledger!$F$2:$F$846,$B6,Ledger!$C$2:$C$846,E$4) | F6: =SUMIFS(Ledger!$E$2:$E$846,Ledger!$A$2:$A$846,$A6,Ledger!$F$2:$F$846,$B6,Ledger!$C$2:$C$846,F$4) | G6: =SUM(C6:F6)
A7: golf | B7: 2025 | C7: =SUMIFS(Ledger!$E$2:$E$846,Ledger!$A$2:$A$846,$A7,Ledger!$F$2:$F$846,$B7,Ledger!$C$2:$C$846,C$4) | D7: =SUMIFS(Ledger!$E$2:$E$846,Ledger!$A$2:$A$846,$A7,Ledger!$F$2:$F$846,$B7,Ledger!$C$2:$C$846,D$4) | E7: =SUMIFS(Ledger!$E$2:$E$846,Ledger!$A$2:$A$846,$A7,Ledger!$F$2:$F$846,$B7,Ledger!$C$2:$C$846,E$4) | F7: =SUMIFS(Ledger!$E$2:$E$846,Ledger!$A$2:$A$846,$A7,Ledger!$F$2:$F$846,$B7,Ledger!$C$2:$C$846,F$4) | G7: =SUM(C7:F7)
A8: golf | B8: 2026 | C8: =SUMIFS(Ledger!$E$2:$E$846,Ledger!$A$2:$A$846,$A8,Ledger!$F$2:$F$846,$B8,Ledger!$C$2:$C$846,C$4) | D8: =SUMIFS(Ledger!$E$2:$E$846,Ledger!$A$2:$A$846,$A8,Ledger!$F$2:$F$846,$B8,Ledger!$C$2:$C$846,D$4) | E8: =SUMIFS(Ledger!$E$2:$E$846,Ledger!$A$2:$A$846,$A8,Ledger!$F$2:$F$846,$B8,Ledger!$C$2:$C$846,E$4) | F8: =SUMIFS(Ledger!$E$2:$E$846,Ledger!$A$2:$A$846,$A8,Ledger!$F$2:$F$846,$B8,Ledger!$C$2:$C$846,F$4) | G8: =SUM(C8:F8)
A9: ev | B9: 2024 | C9: =SUMIFS(Ledger!$E$2:$E$846,Ledger!$A$2:$A$846,$A9,Ledger!$F$2:$F$846,$B9,Ledger!$C$2:$C$846,C$4) | D9: =SUMIFS(Ledger!$E$2:$E$846,Ledger!$A$2:$A$846,$A9,Ledger!$F$2:$F$846,$B9,Ledger!$C$2:$C$846,D$4) | E9: =SUMIFS(Ledger!$E$2:$E$846,Ledger!$A$2:$A$846,$A9,Ledger!$F$2:$F$846,$B9,Ledger!$C$2:$C$846,E$4) | F9: =SUMIFS(Ledger!$E$2:$E$846,Ledger!$A$2:$A$846,$A9,Ledger!$F$2:$F$846,$B9,Ledger!$C$2:$C$846,F$4) | G9: =SUM(C9:F9)
A10: ev | B10: 2025 | C10: =SUMIFS(Ledger!$E$2:$E$846,Ledger!$A$2:$A$846,$A10,Ledger!$F$2:$F$846,$B10,Ledger!$C$2:$C$846,C$4) | D10: =SUMIFS(Ledger!$E$2:$E$846,Ledger!$A$2:$A$846,$A10,Ledger!$F$2:$F$846,$B10,Ledger!$C$2:$C$846,D$4) | E10: =SUMIFS(Ledger!$E$2:$E$846,Ledger!$A$2:$A$846,$A10,Ledger!$F$2:$F$846,$B10,Ledger!$C$2:$C$846,E$4) | F10: =SUMIFS(Ledger!$E$2:$E$846,Ledger!$A$2:$A$846,$A10,Ledger!$F$2:$F$846,$B10,Ledger!$C$2:$C$846,F$4) | G10: =SUM(C10:F10)
A11: ev | B11: 2026 | C11: =SUMIFS(Ledger!$E$2:$E$846,Ledger!$A$2:$A$846,$A11,Ledger!$F$2:$F$846,$B11,Ledger!$C$2:$C$846,C$4) | D11: =SUMIFS(Ledger!$E$2:$E$846,Ledger!$A$2:$A$846,$A11,Ledger!$F$2:$F$846,$B11,Ledger!$C$2:$C$846,D$4) | E11: =SUMIFS(Ledger!$E$2:$E$846,Ledger!$A$2:$A$846,$A11,Ledger!$F$2:$F$846,$B11,Ledger!$C$2:$C$846,E$4) | F11: =SUMIFS(Ledger!$E$2:$E$846,Ledger!$A$2:$A$846,$A11,Ledger!$F$2:$F$846,$B11,Ledger!$C$2:$C$846,F$4) | G11: =SUM(C11:F11)
A12: focus | B12: 2023 | C12: =SUMIFS(Ledger!$E$2:$E$846,Ledger!$A$2:$A$846,$A12,Ledger!$F$2:$F$846,$B12,Ledger!$C$2:$C$846,C$4) | D12: =SUMIFS(Ledger!$E$2:$E$846,Ledger!$A$2:$A$846,$A12,Ledger!$F$2:$F$846,$B12,Ledger!$C$2:$C$846,D$4) | E12: =SUMIFS(Ledger!$E$2:$E$846,Ledger!$A$2:$A$846,$A12,Ledger!$F$2:$F$846,$B12,Ledger!$C$2:$C$846,E$4) | F12: =SUMIFS(Ledger!$E$2:$E$846,Ledger!$A$2:$A$846,$A12,Ledger!$F$2:$F$846,$B12,Ledger!$C$2:$C$846,F$4) | G12: =SUM(C12:F12)
A13: focus | B13: 2024 | C13: =SUMIFS(Ledger!$E$2:$E$846,Ledger!$A$2:$A$846,$A13,Ledger!$F$2:$F$846,$B13,Ledger!$C$2:$C$846,C$4) | D13: =SUMIFS(Ledger!$E$2:$E$846,Ledger!$A$2:$A$846,$A13,Ledger!$F$2:$F$846,$B13,Ledger!$C$2:$C$846,D$4) | E13: =SUMIFS(Ledger!$E$2:$E$846,Ledger!$A$2:$A$846,$A13,Ledger!$F$2:$F$846,$B13,Ledger!$C$2:$C$846,E$4) | F13: =SUMIFS(Ledger!$E$2:$E$846,Ledger!$A$2:$A$846,$A13,Ledger!$F$2:$F$846,$B13,Ledger!$C$2:$C$846,F$4) | G13: =SUM(C13:F13)
A14: focus | B14: 2025 | C14: =SUMIFS(Ledger!$E$2:$E$846,Ledger!$A$2:$A$846,$A14,Ledger!$F$2:$F$846,$B14,Ledger!$C$2:$C$846,C$4) | D14: =SUMIFS(Ledger!$E$2:$E$846,Ledger!$A$2:$A$846,$A14,Ledger!$F$2:$F$846,$B14,Ledger!$C$2:$C$846,D$4) | E14: =SUMIFS(Ledger!$E$2:$E$846,Ledger!$A$2:$A$846,$A14,Ledger!$F$2:$F$846,$B14,Ledger!$C$2:$C$846,E$4) | F14: =SUMIFS(Ledger!$E$2:$E$846,Ledger!$A$2:$A$846,$A14,Ledger!$F$2:$F$846,$B14,Ledger!$C$2:$C$846,F$4) | G14: =SUM(C14:F14)
A15: focus | B15: 2026 | C15: =SUMIFS(Ledger!$E$2:$E$846,Ledger!$A$2:$A$846,$A15,Ledger!$F$2:$F$846,$B15,Ledger!$C$2:$C$846,C$4) | D15: =SUMIFS(Ledger!$E$2:$E$846,Ledger!$A$2:$A$846,$A15,Ledger!$F$2:$F$846,$B15,Ledger!$C$2:$C$846,D$4) | E15: =SUMIFS(Ledger!$E$2:$E$846,Ledger!$A$2:$A$846,$A15,Ledger!$F$2:$F$846,$B15,Ledger!$C$2:$C$846,E$4) | F15: =SUMIFS(Ledger!$E$2:$E$846,Ledger!$A$2:$A$846,$A15,Ledger!$F$2:$F$846,$B15,Ledger!$C$2:$C$846,F$4) | G15: =SUM(C15:F15)
A16: corolla | B16: 2023 | C16: =SUMIFS(Ledger!$E$2:$E$846,Ledger!$A$2:$A$846,$A16,Ledger!$F$2:$F$846,$B16,Ledger!$C$2:$C$846,C$4) | D16: =SUMIFS(Ledger!$E$2:$E$846,Ledger!$A$2:$A$846,$A16,Ledger!$F$2:$F$846,$B16,Ledger!$C$2:$C$846,D$4) | E16: =SUMIFS(Ledger!$E$2:$E$846,Ledger!$A$2:$A$846,$A16,Ledger!$F$2:$F$846,$B16,Ledger!$C$2:$C$846,E$4) | F16: =SUMIFS(Ledger!$E$2:$E$846,Ledger!$A$2:$A$846,$A16,Ledger!$F$2:$F$846,$B16,Ledger!$C$2:$C$846,F$4) | G16: =SUM(C16:F16)
... A19: corolla | B19: 2026 | C19: =SUMIFS(Ledger!$E$2:$E$846,Ledger!$A$2:$A$846,$A19,Ledger!$F$2:$F$846,$B19,Ledger!$C$2:$C$846,C$4) | D19: =SUMIFS(Ledger!$E$2:$E$846,Ledger!$A$2:$A$846,$A19,Ledger!$F$2:$F$846,$B19,Ledger!$C$2:$C$846,D$4) | E19: =SUMIFS(Ledger!$E$2:$E$846,Ledger!$A$2:$A$846,$A19,Ledger!$F$2:$F$846,$B19,Ledger!$C$2:$C$846,E$4) | F19: =SUMIFS(Ledger!$E$2:$E$846,Ledger!$A$2:$A$846,$A19,Ledger!$F$2:$F$846,$B19,Ledger!$C$2:$C$846,F$4) | G19: =SUM(C19:F19)

Sheet Ledger
A1: vehicle | B1: date | C1: group | D1: source | E1: amount | F1: year | G1: currency | H1: category
A2: =fillups!A2 | B2: =LEFT(fillups!C2,10) | C2: fuel | D2: fillups | E2: =fillups!H2 | F2: =IF(B2="","",LEFT(B2,4)) | G2: =IF(A2="","",INDEX(vehicles!$I$2:$I$5,MATCH(A2,vehicles!$A$2:$A$5,0))) | H2: fuel
A3: =fillups!A3 | B3: =LEFT(fillups!C3,10) | C3: fuel | D3: fillups | E3: =fillups!H3 | F3: =IF(B3="","",LEFT(B3,4)) | G3: =IF(A3="","",INDEX(vehicles!$I$2:$I$5,MATCH(A3,vehicles!$A$2:$A$5,0))) | H3: fuel
A4: =fillups!A4 | B4: =LEFT(fillups!C4,10) | C4: fuel | D4: fillups | E4: =fillups!H4 | F4: =IF(B4="","",LEFT(B4,4)) | G4: =IF(A4="","",INDEX(vehicles!$I$2:$I$5,MATCH(A4,vehicles!$A$2:$A$5,0))) | H4: fuel
A5: =fillups!A5 | B5: =LEFT(fillups!C5,10) | C5: fuel | D5: fillups | E5: =fillups!H5 | F5: =IF(B5="","",LEFT(B5,4)) | G5: =IF(A5="","",INDEX(vehicles!$I$2:$I$5,MATCH(A5,vehicles!$A$2:$A$5,0))) | H5: fuel
A6: =fillups!A6 | B6: =LEFT(fillups!C6,10) | C6: fuel | D6: fillups | E6: =fillups!H6 | F6: =IF(B6="","",LEFT(B6,4)) | G6: =IF(A6="","",INDEX(vehicles!$I$2:$I$5,MATCH(A6,vehicles!$A$2:$A$5,0))) | H6: fuel
A7: =fillups!A7 | B7: =LEFT(fillups!C7,10) | C7: fuel | D7: fillups | E7: =fillups!H7 | F7: =IF(B7="","",LEFT(B7,4)) | G7: =IF(A7="","",INDEX(vehicles!$I$2:$I$5,MATCH(A7,vehicles!$A$2:$A$5,0))) | H7: fuel
A8: =fillups!A8 | B8: =LEFT(fillups!C8,10) | C8: fuel | D8: fillups | E8: =fillups!H8 | F8: =IF(B8="","",LEFT(B8,4)) | G8: =IF(A8="","",INDEX(vehicles!$I$2:$I$5,MATCH(A8,vehicles!$A$2:$A$5,0))) | H8: fuel
A9: =fillups!A9 | B9: =LEFT(fillups!C9,10) | C9: fuel | D9: fillups | E9: =fillups!H9 | F9: =IF(B9="","",LEFT(B9,4)) | G9: =IF(A9="","",INDEX(vehicles!$I$2:$I$5,MATCH(A9,vehicles!$A$2:$A$5,0))) | H9: fuel
A10: =fillups!A10 | B10: =LEFT(fillups!C10,10) | C10: fuel | D10: fillups | E10: =fillups!H10 | F10: =IF(B10="","",LEFT(B10,4)) | G10: =IF(A10="","",INDEX(vehicles!$I$2:$I$5,MATCH(A10,vehicles!$A$2:$A$5,0))) | H10: fuel
A11: =fillups!A11 | B11: =LEFT(fillups!C11,10) | C11: fuel | D11: fillups | E11: =fillups!H11 | F11: =IF(B11="","",LEFT(B11,4)) | G11: =IF(A11="","",INDEX(vehicles!$I$2:$I$5,MATCH(A11,vehicles!$A$2:$A$5,0))) | H11: fuel
A12: =fillups!A12 | B12: =LEFT(fillups!C12,10) | C12: fuel | D12: fillups | E12: =fillups!H12 | F12: =IF(B12="","",LEFT(B12,4)) | G12: =IF(A12="","",INDEX(vehicles!$I$2:$I$5,MATCH(A12,vehicles!$A$2:$A$5,0))) | H12: fuel
A13: =fillups!A13 | B13: =LEFT(fillups!C13,10) | C13: fuel | D13: fillups | E13: =fillups!H13 | F13: =IF(B13="","",LEFT(B13,4)) | G13: =IF(A13="","",INDEX(vehicles!$I$2:$I$5,MATCH(A13,vehicles!$A$2:$A$5,0))) | H13: fuel
... A596: =fillups!A596 | B596: =LEFT(fillups!C596,10) | C596: fuel | D596: fillups | E596: =fillups!H596 | F596: =IF(B596="","",LEFT(B596,4)) | G596: =IF(A596="","",INDEX(vehicles!$I$2:$I$5,MATCH(A596,vehicles!$A$2:$A$5,0))) | H596: fuel
A597: =expenses!A2 | B597: =LEFT(expenses!B2,10) | C597: other | D597: expenses | E597: =expenses!D2 | F597: =IF(B597="","",LEFT(B597,4)) | G597: =IF(A597="","",INDEX(vehicles!$I$2:$I$5,MATCH(A597,vehicles!$A$2:$A$5,0))) | H597: =expenses!C2
A598: =expenses!A3 | B598: =LEFT(expenses!B3,10) | C598: other | D598: expenses | E598: =expenses!D3 | F598: =IF(B598="","",LEFT(B598,4)) | G598: =IF(A598="","",INDEX(vehicles!$I$2:$I$5,MATCH(A598,vehicles!$A$2:$A$5,0))) | H598: =expenses!C3
A599: =expenses!A4 | B599: =LEFT(expenses!B4,10) | C599: other | D599: expenses | E599: =expenses!D4 | F599: =IF(B599="","",LEFT(B599,4)) | G599: =IF(A599="","",INDEX(vehicles!$I$2:$I$5,MATCH(A599,vehicles!$A$2:$A$5,0))) | H599: =expenses!C4
A600: =expenses!A5 | B600: =LEFT(expenses!B5,10) | C600: other | D600: expenses | E600: =expenses!D5 | F600: =IF(B600="","",LEFT(B600,4)) | G600: =IF(A600="","",INDEX(vehicles!$I$2:$I$5,MATCH(A600,vehicles!$A$2:$A$5,0))) | H600: =expenses!C5
A601: =expenses!A6 | B601: =LEFT(expenses!B6,10) | C601: other | D601: expenses | E601: =expenses!D6 | F601: =IF(B601="","",LEFT(B601,4)) | G601: =IF(A601="","",INDEX(vehicles!$I$2:$I$5,MATCH(A601,vehicles!$A$2:$A$5,0))) | H601: =expenses!C6
A602: =expenses!A7 | B602: =LEFT(expenses!B7,10) | C602: other | D602: expenses | E602: =expenses!D7 | F602: =IF(B602="","",LEFT(B602,4)) | G602: =IF(A602="","",INDEX(vehicles!$I$2:$I$5,MATCH(A602,vehicles!$A$2:$A$5,0))) | H602: =expenses!C7
A603: =expenses!A8 | B603: =LEFT(expenses!B8,10) | C603: other | D603: expenses | E603: =expenses!D8 | F603: =IF(B603="","",LEFT(B603,4)) | G603: =IF(A603="","",INDEX(vehicles!$I$2:$I$5,MATCH(A603,vehicles!$A$2:$A$5,0))) | H603: =expenses!C8
A604: =expenses!A9 | B604: =LEFT(expenses!B9,10) | C604: other | D604: expenses | E604: =expenses!D9 | F604: =IF(B604="","",LEFT(B604,4)) | G604: =IF(A604="","",INDEX(vehicles!$I$2:$I$5,MATCH(A604,vehicles!$A$2:$A$5,0))) | H604: =expenses!C9
A605: =expenses!A10 | B605: =LEFT(expenses!B10,10) | C605: other | D605: expenses | E605: =expenses!D10 | F605: =IF(B605="","",LEFT(B605,4)) | G605: =IF(A605="","",INDEX(vehicles!$I$2:$I$5,MATCH(A605,vehicles!$A$2:$A$5,0))) | H605: =expenses!C10
A606: =expenses!A11 | B606: =LEFT(expenses!B11,10) | C606: other | D606: expenses | E606: =expenses!D11 | F606: =IF(B606="","",LEFT(B606,4)) | G606: =IF(A606="","",INDEX(vehicles!$I$2:$I$5,MATCH(A606,vehicles!$A$2:$A$5,0))) | H606: =expenses!C11
A607: =expenses!A12 | B607: =LEFT(expenses!B12,10) | C607: other | D607: expenses | E607: =expenses!D12 | F607: =IF(B607="","",LEFT(B607,4)) | G607: =IF(A607="","",INDEX(vehicles!$I$2:$I$5,MATCH(A607,vehicles!$A$2:$A$5,0))) | H607: =expenses!C12
A608: =expenses!A13 | B608: =LEFT(expenses!B13,10) | C608: other | D608: expenses | E608: =expenses!D13 | F608: =IF(B608="","",LEFT(B608,4)) | G608: =IF(A608="","",INDEX(vehicles!$I$2:$I$5,MATCH(A608,vehicles!$A$2:$A$5,0))) | H608: =expenses!C13
... A752: =expenses!A157 | B752: =LEFT(expenses!B157,10) | C752: other | D752: expenses | E752: =expenses!D157 | F752: =IF(B752="","",LEFT(B752,4)) | G752: =IF(A752="","",INDEX(vehicles!$I$2:$I$5,MATCH(A752,vehicles!$A$2:$A$5,0))) | H752: =expenses!C157
A753: =maintenance!A2 | B753: =LEFT(maintenance!B2,10) | C753: maintenance | D753: maintenance | E753: =maintenance!E2 | F753: =IF(B753="","",LEFT(B753,4)) | G753: =IF(A753="","",INDEX(vehicles!$I$2:$I$5,MATCH(A753,vehicles!$A$2:$A$5,0))) | H753: maintenance
A754: =maintenance!A3 | B754: =LEFT(maintenance!B3,10) | C754: maintenance | D754: maintenance | E754: =maintenance!E3 | F754: =IF(B754="","",LEFT(B754,4)) | G754: =IF(A754="","",INDEX(vehicles!$I$2:$I$5,MATCH(A754,vehicles!$A$2:$A$5,0))) | H754: maintenance
A755: =maintenance!A4 | B755: =LEFT(maintenance!B4,10) | C755: maintenance | D755: maintenance | E755: =maintenance!E4 | F755: =IF(B755="","",LEFT(B755,4)) | G755: =IF(A755="","",INDEX(vehicles!$I$2:$I$5,MATCH(A755,vehicles!$A$2:$A$5,0))) | H755: maintenance
A756: =maintenance!A5 | B756: =LEFT(maintenance!B5,10) | C756: maintenance | D756: maintenance | E756: =maintenance!E5 | F756: =IF(B756="","",LEFT(B756,4)) | G756: =IF(A756="","",INDEX(vehicles!$I$2:$I$5,MATCH(A756,vehicles!$A$2:$A$5,0))) | H756: maintenance
A757: =maintenance!A6 | B757: =LEFT(maintenance!B6,10) | C757: maintenance | D757: maintenance | E757: =maintenance!E6 | F757: =IF(B757="","",LEFT(B757,4)) | G757: =IF(A757="","",INDEX(vehicles!$I$2:$I$5,MATCH(A757,vehicles!$A$2:$A$5,0))) | H757: maintenance
A758: =maintenance!A7 | B758: =LEFT(maintenance!B7,10) | C758: maintenance | D758: maintenance | E758: =maintenance!E7 | F758: =IF(B758="","",LEFT(B758,4)) | G758: =IF(A758="","",INDEX(vehicles!$I$2:$I$5,MATCH(A758,vehicles!$A$2:$A$5,0))) | H758: maintenance
A759: =maintenance!A8 | B759: =LEFT(maintenance!B8,10) | C759: maintenance | D759: maintenance | E759: =maintenance!E8 | F759: =IF(B759="","",LEFT(B759,4)) | G759: =IF(A759="","",INDEX(vehicles!$I$2:$I$5,MATCH(A759,vehicles!$A$2:$A$5,0))) | H759: maintenance
A760: =maintenance!A9 | B760: =LEFT(maintenance!B9,10) | C760: maintenance | D760: maintenance | E760: =maintenance!E9 | F760: =IF(B760="","",LEFT(B760,4)) | G760: =IF(A760="","",INDEX(vehicles!$I$2:$I$5,MATCH(A760,vehicles!$A$2:$A$5,0))) | H760: maintenance
A761: =maintenance!A10 | B761: =LEFT(maintenance!B10,10) | C761: maintenance | D761: maintenance | E761: =maintenance!E10 | F761: =IF(B761="","",LEFT(B761,4)) | G761: =IF(A761="","",INDEX(vehicles!$I$2:$I$5,MATCH(A761,vehicles!$A$2:$A$5,0))) | H761: maintenance
A762: =maintenance!A11 | B762: =LEFT(maintenance!B11,10) | C762: maintenance | D762: maintenance | E762: =maintenance!E11 | F762: =IF(B762="","",LEFT(B762,4)) | G762: =IF(A762="","",INDEX(vehicles!$I$2:$I$5,MATCH(A762,vehicles!$A$2:$A$5,0))) | H762: maintenance
A763: =maintenance!A12 | B763: =LEFT(maintenance!B12,10) | C763: maintenance | D763: maintenance | E763: =maintenance!E12 | F763: =IF(B763="","",LEFT(B763,4)) | G763: =IF(A763="","",INDEX(vehicles!$I$2:$I$5,MATCH(A763,vehicles!$A$2:$A$5,0))) | H763: maintenance
A764: =maintenance!A13 | B764: =LEFT(maintenance!B13,10) | C764: maintenance | D764: maintenance | E764: =maintenance!E13 | F764: =IF(B764="","",LEFT(B764,4)) | G764: =IF(A764="","",INDEX(vehicles!$I$2:$I$5,MATCH(A764,vehicles!$A$2:$A$5,0))) | H764: maintenance
... A767: =maintenance!A16 | B767: =LEFT(maintenance!B16,10) | C767: maintenance | D767: maintenance | E767: =maintenance!E16 | F767: =IF(B767="","",LEFT(B767,4)) | G767: =IF(A767="","",INDEX(vehicles!$I$2:$I$5,MATCH(A767,vehicles!$A$2:$A$5,0))) | H767: maintenance
A768: =documents!A2 | B768: =LEFT(documents!E2,10) | C768: compliance | D768: documents | E768: =documents!G2 | F768: =IF(B768="","",LEFT(B768,4)) | G768: =IF(A768="","",INDEX(vehicles!$I$2:$I$5,MATCH(A768,vehicles!$A$2:$A$5,0))) | H768: documents
A769: =documents!A3 | B769: =LEFT(documents!E3,10) | C769: compliance | D769: documents | E769: =documents!G3 | F769: =IF(B769="","",LEFT(B769,4)) | G769: =IF(A769="","",INDEX(vehicles!$I$2:$I$5,MATCH(A769,vehicles!$A$2:$A$5,0))) | H769: documents
A770: =documents!A4 | B770: =LEFT(documents!E4,10) | C770: compliance | D770: documents | E770: =documents!G4 | F770: =IF(B770="","",LEFT(B770,4)) | G770: =IF(A770="","",INDEX(vehicles!$I$2:$I$5,MATCH(A770,vehicles!$A$2:$A$5,0))) | H770: documents
A771: =documents!A5 | B771: =LEFT(documents!E5,10) | C771: compliance | D771: documents | E771: =documents!G5 | F771: =IF(B771="","",LEFT(B771,4)) | G771: =IF(A771="","",INDEX(vehicles!$I$2:$I$5,MATCH(A771,vehicles!$A$2:$A$5,0))) | H771: documents
A772: =documents!A6 | B772: =LEFT(documents!E6,10) | C772: compliance | D772: documents | E772: =documents!G6 | F772: =IF(B772="","",LEFT(B772,4)) | G772: =IF(A772="","",INDEX(vehicles!$I$2:$I$5,MATCH(A772,vehicles!$A$2:$A$5,0))) | H772: documents
A773: =documents!A7 | B773: =LEFT(documents!E7,10) | C773: compliance | D773: documents | E773: =documents!G7 | F773: =IF(B773="","",LEFT(B773,4)) | G773: =IF(A773="","",INDEX(vehicles!$I$2:$I$5,MATCH(A773,vehicles!$A$2:$A$5,0))) | H773: documents
A774: =documents!A8 | B774: =LEFT(documents!E8,10) | C774: compliance | D774: documents | E774: =documents!G8 | F774: =IF(B774="","",LEFT(B774,4)) | G774: =IF(A774="","",INDEX(vehicles!$I$2:$I$5,MATCH(A774,vehicles!$A$2:$A$5,0))) | H774: documents
A775: =documents!A9 | B775: =LEFT(documents!E9,10) | C775: compliance | D775: documents | E775: =documents!G9 | F775: =IF(B775="","",LEFT(B775,4)) | G775: =IF(A775="","",INDEX(vehicles!$I$2:$I$5,MATCH(A775,vehicles!$A$2:$A$5,0))) | H775: documents
A776: =documents!A10 | B776: =LEFT(documents!E10,10) | C776: compliance | D776: documents | E776: =documents!G10 | F776: =IF(B776="","",LEFT(B776,4)) | G776: =IF(A776="","",INDEX(vehicles!$I$2:$I$5,MATCH(A776,vehicles!$A$2:$A$5,0))) | H776: documents
A777: =documents!A11 | B777: =LEFT(documents!E11,10) | C777: compliance | D777: documents | E777: =documents!G11 | F777: =IF(B777="","",LEFT(B777,4)) | G777: =IF(A777="","",INDEX(vehicles!$I$2:$I$5,MATCH(A777,vehicles!$A$2:$A$5,0))) | H777: documents
A778: =documents!A12 | B778: =LEFT(documents!E12,10) | C778: compliance | D778: documents | E778: =documents!G12 | F778: =IF(B778="","",LEFT(B778,4)) | G778: =IF(A778="","",INDEX(vehicles!$I$2:$I$5,MATCH(A778,vehicles!$A$2:$A$5,0))) | H778: documents
A779: =documents!A13 | B779: =LEFT(documents!E13,10) | C779: compliance | D779: documents | E779: =documents!G13 | F779: =IF(B779="","",LEFT(B779,4)) | G779: =IF(A779="","",INDEX(vehicles!$I$2:$I$5,MATCH(A779,vehicles!$A$2:$A$5,0))) | H779: documents
... A786: =documents!A20 | B786: =LEFT(documents!E20,10) | C786: compliance | D786: documents | E786: =documents!G20 | F786: =IF(B786="","",LEFT(B786,4)) | G786: =IF(A786="","",INDEX(vehicles!$I$2:$I$5,MATCH(A786,vehicles!$A$2:$A$5,0))) | H786: documents
C787: other | D787: finance | F787: =IF(B787="","",LEFT(B787,4)) | G787: =IF(A787="","",INDEX(vehicles!$I$2:$I$5,MATCH(A787,vehicles!$A$2:$A$5,0))) | H787: finance | J787: Finance lines: yours to add (interest shares and fees on their dates, the end adjustment; spec §7.32). Group "other", category "finance".
C788: other | D788: finance | F788: =IF(B788="","",LEFT(B788,4)) | G788: =IF(A788="","",INDEX(vehicles!$I$2:$I$5,MATCH(A788,vehicles!$A$2:$A$5,0))) | H788: finance
C789: other | D789: finance | F789: =IF(B789="","",LEFT(B789,4)) | G789: =IF(A789="","",INDEX(vehicles!$I$2:$I$5,MATCH(A789,vehicles!$A$2:$A$5,0))) | H789: finance
C790: other | D790: finance | F790: =IF(B790="","",LEFT(B790,4)) | G790: =IF(A790="","",INDEX(vehicles!$I$2:$I$5,MATCH(A790,vehicles!$A$2:$A$5,0))) | H790: finance
C791: other | D791: finance | F791: =IF(B791="","",LEFT(B791,4)) | G791: =IF(A791="","",INDEX(vehicles!$I$2:$I$5,MATCH(A791,vehicles!$A$2:$A$5,0))) | H791: finance
C792: other | D792: finance | F792: =IF(B792="","",LEFT(B792,4)) | G792: =IF(A792="","",INDEX(vehicles!$I$2:$I$5,MATCH(A792,vehicles!$A$2:$A$5,0))) | H792: finance
C793: other | D793: finance | F793: =IF(B793="","",LEFT(B793,4)) | G793: =IF(A793="","",INDEX(vehicles!$I$2:$I$5,MATCH(A793,vehicles!$A$2:$A$5,0))) | H793: finance
C794: other | D794: finance | F794: =IF(B794="","",LEFT(B794,4)) | G794: =IF(A794="","",INDEX(vehicles!$I$2:$I$5,MATCH(A794,vehicles!$A$2:$A$5,0))) | H794: finance
C795: other | D795: finance | F795: =IF(B795="","",LEFT(B795,4)) | G795: =IF(A795="","",INDEX(vehicles!$I$2:$I$5,MATCH(A795,vehicles!$A$2:$A$5,0))) | H795: finance
C796: other | D796: finance | F796: =IF(B796="","",LEFT(B796,4)) | G796: =IF(A796="","",INDEX(vehicles!$I$2:$I$5,MATCH(A796,vehicles!$A$2:$A$5,0))) | H796: finance
C797: other | D797: finance | F797: =IF(B797="","",LEFT(B797,4)) | G797: =IF(A797="","",INDEX(vehicles!$I$2:$I$5,MATCH(A797,vehicles!$A$2:$A$5,0))) | H797: finance
C798: other | D798: finance | F798: =IF(B798="","",LEFT(B798,4)) | G798: =IF(A798="","",INDEX(vehicles!$I$2:$I$5,MATCH(A798,vehicles!$A$2:$A$5,0))) | H798: finance
C799: other | D799: finance | F799: =IF(B799="","",LEFT(B799,4)) | G799: =IF(A799="","",INDEX(vehicles!$I$2:$I$5,MATCH(A799,vehicles!$A$2:$A$5,0))) | H799: finance
... C846: other | D846: finance | F846: =IF(B846="","",LEFT(B846,4)) | G846: =IF(A846="","",INDEX(vehicles!$I$2:$I$5,MATCH(A846,vehicles!$A$2:$A$5,0))) | H846: finance

Sheet expected
A1: id | B1: figure | C1: viewer | D1: vehicle | E1: period | F1: currency | G1: unit | H1: expected | I1: source | J1: notes | K1: how
A2: 1 | B2: ownership.total | C2: alex | D2: golf | E2: since_bought | F2: GBP | G2: money | I2: spreadsheet+script | K2: yours
A3: 2 | B3: ownership.running | C3: alex | D3: golf | E3: since_bought | F3: GBP | G3: money | I3: spreadsheet | K3: yours
A4: 3 | B4: ownership.depreciation | C4: alex | D4: golf | E4: since_bought | F4: GBP | G4: money | I4: spreadsheet+script | K4: yours
A5: 4 | B5: ownership.per_distance | C5: alex | D5: golf | E5: since_bought | F5: GBP | G5: money/mi | I5: spreadsheet+script | K5: yours
A6: 5 | B6: ownership.per_month | C6: alex | D6: golf | E6: since_bought | F6: GBP | G6: money/month | I6: spreadsheet+script | K6: yours
A7: 6 | B7: ownership.total | C7: alex | D7: ev | E7: since_bought | F7: GBP | G7: money | I7: spreadsheet+script | K7: yours
A8: 7 | B8: ownership.running | C8: alex | D8: ev | E8: since_bought | F8: GBP | G8: money | I8: spreadsheet | K8: yours
A9: 8 | B9: ownership.depreciation | C9: alex | D9: ev | E9: since_bought | F9: GBP | G9: money | I9: spreadsheet+script | K9: yours
A10: 9 | B10: ownership.per_distance | C10: alex | D10: ev | E10: since_bought | F10: GBP | G10: money/mi | I10: spreadsheet+script | K10: yours
A11: 10 | B11: ownership.per_month | C11: alex | D11: ev | E11: since_bought | F11: GBP | G11: money/month | I11: spreadsheet+script | K11: yours
A12: 11 | B12: ownership.total | C12: alex | D12: focus | E12: since_bought | F12: GBP | G12: money | I12: spreadsheet+script | K12: yours
A13: 12 | B13: ownership.running | C13: alex | D13: focus | E13: since_bought | F13: GBP | G13: money | I13: spreadsheet | K13: yours
... A233: 232 | B233: true_cost.what_changed.total | C233: alex | D233: corolla | E233: last_12_months_vs_previous | F233: EUR | G233: money/mi | I233: spreadsheet+script | K233: yours
A234: 233 | B234: finance.payments_made | C234: alex | D234: golf | E234: today | F234: GBP | G234: count | I234: spreadsheet+script | J234: golf-pcp | K234: yours
A235: 234 | B235: finance.payments_remaining | C235: alex | D235: golf | E235: today | F235: GBP | G235: count | I235: spreadsheet+script | J235: golf-pcp | K235: yours
A236: 235 | B236: finance.amount_paid | C236: alex | D236: golf | E236: today | F236: GBP | G236: money | I236: spreadsheet+script | J236: golf-pcp | K236: yours
A237: 236 | B237: finance.interest_so_far | C237: alex | D237: golf | E237: today | F237: GBP | G237: money | I237: spreadsheet+script | J237: golf-pcp | K237: yours
A238: 237 | B238: finance.cost_of_credit | C238: alex | D238: golf | E238: today | F238: GBP | G238: money | I238: spreadsheet+script | J238: golf-pcp | K238: yours
A239: 238 | B239: finance.payments_made | C239: alex | D239: ev | E239: today | F239: GBP | G239: count | I239: spreadsheet+script | J239: ev-hp | K239: yours
A240: 239 | B240: finance.payments_remaining | C240: alex | D240: ev | E240: today | F240: GBP | G240: count | I240: spreadsheet+script | J240: ev-hp | K240: yours
A241: 240 | B241: finance.amount_paid | C241: alex | D241: ev | E241: today | F241: GBP | G241: money | I241: spreadsheet+script | J241: ev-hp | K241: yours
A242: 241 | B242: finance.interest_so_far | C242: alex | D242: ev | E242: today | F242: GBP | G242: money | I242: spreadsheet+script | J242: ev-hp | K242: yours
A243: 242 | B243: finance.cost_of_credit | C243: alex | D243: ev | E243: today | F243: GBP | G243: money | I243: spreadsheet+script | J243: ev-hp | K243: yours
A244: 243 | B244: finance.settlement_estimate | C244: alex | D244: ev | E244: today | F244: GBP | G244: money | I244: spreadsheet+script | J244: ev-hp | K244: yours
A245: 244 | B245: finance.equity | C245: alex | D245: ev | E245: today | F245: GBP | G245: money | I245: spreadsheet+script | J245: ev-hp | K245: yours
A246: 245 | B246: claim.business_distance | C246: alex | D246: golf | E246: tax_year 2023-24 | G246: mi | H246: =ROUND(SUMIFS(trips!$L$2:$L$144,trips!$I$2:$I$144,"yes",trips!$K$2:$K$144,"2023-24"),0) | I246: spreadsheet | K246: example formula (Claude): check it, or replace it with your own
A247: 246 | B247: claim.amount | C247: alex | D247: golf | E247: tax_year 2023-24 | F247: GBP | G247: money | I247: spreadsheet | K247: yours
A248: 247 | B248: claim.business_distance | C248: alex | D248: golf | E248: tax_year 2024-25 | G248: mi | H248: =ROUND(SUMIFS(trips!$L$2:$L$144,trips!$I$2:$I$144,"yes",trips!$K$2:$K$144,"2024-25"),0) | I248: spreadsheet | K248: example formula (Claude): check it, or replace it with your own
A249: 248 | B249: claim.amount | C249: alex | D249: golf | E249: tax_year 2024-25 | F249: GBP | G249: money | I249: spreadsheet | K249: yours
A250: 249 | B250: claim.business_distance | C250: alex | D250: golf | E250: tax_year 2025-26 | G250: mi | H250: =ROUND(SUMIFS(trips!$L$2:$L$144,trips!$I$2:$I$144,"yes",trips!$K$2:$K$144,"2025-26"),0) | I250: spreadsheet | K250: example formula (Claude): check it, or replace it with your own
A251: 250 | B251: claim.amount | C251: alex | D251: golf | E251: tax_year 2025-26 | F251: GBP | G251: money | I251: spreadsheet | K251: yours
A252: 251 | B252: claim.business_distance | C252: alex | D252: golf | E252: tax_year 2026-27 | G252: mi | H252: =ROUND(SUMIFS(trips!$L$2:$L$144,trips!$I$2:$I$144,"yes",trips!$K$2:$K$144,"2026-27"),0) | I252: spreadsheet | K252: example formula (Claude): check it, or replace it with your own
A253: 252 | B253: claim.amount | C253: alex | D253: golf | E253: tax_year 2026-27 | F253: GBP | G253: money | I253: spreadsheet | K253: yours
A254: 253 | B254: coming_up.total | C254: alex | D254: all | E254: next_3_months | F254: GBP | G254: money | I254: spreadsheet | J254: put at_least here when any item has no known cost | K254: yours
A255: 254 | B255: coming_up.total | C255: alex | D255: all | E255: next_12_months | F255: GBP | G255: money | I255: spreadsheet | J255: put at_least here when any item has no known cost | K255: yours
A256: 255 | B256: coming_up.total | C256: alex | D256: all | E256: next_3_months | F256: EUR | G256: money | I256: spreadsheet | J256: put at_least here when any item has no known cost | K256: yours
A257: 256 | B257: coming_up.total | C257: alex | D257: all | E257: next_12_months | F257: EUR | G257: money | I257: spreadsheet | J257: put at_least here when any item has no known cost | K257: yours
A258: 257 | B258: coming_up.total | C258: sam | D258: all | E258: next_3_months | F258: EUR | G258: money | I258: spreadsheet | J258: put at_least here when any item has no known cost | K258: yours
A259: 258 | B259: coming_up.total | C259: sam | D259: all | E259: next_12_months | F259: EUR | G259: money | I259: spreadsheet | J259: put at_least here when any item has no known cost | K259: yours
A260: 259 | B260: economy.lifetime | C260: alex | D260: golf | E260: all_time | G260: l/100km | H260: =ROUND(SUMIFS(fillups!$L$2:$L$596,fillups!$A$2:$A$596,"golf",fillups!$M$2:$M$596,">0")/SUMIFS(fillups!$M$2:$M$596,fillups!$A$2:$A$596,"golf")*100,2) | I260: spreadsheet | K260: example formula (Claude): check it, or replace it with your own
A261: 260 | B261: economy.segment | C261: alex | D261: golf | E261: segment ending 2023-10-30 18:05 | G261: l/100km | H261: =IFERROR(ROUND(INDEX(fillups!$N$2:$N$596,MATCH("golf|2023-10-30 18:05",fillups!$O$2:$O$596,0)),2),"—") | I261: spreadsheet | K261: example formula (Claude): check it, or replace it with your own
A262: 261 | B262: economy.segment | C262: alex | D262: golf | E262: segment ending 2023-11-09 16:53 | G262: l/100km | H262: =IFERROR(ROUND(INDEX(fillups!$N$2:$N$596,MATCH("golf|2023-11-09 16:53",fillups!$O$2:$O$596,0)),2),"—") | I262: spreadsheet | K262: example formula (Claude): check it, or replace it with your own
A263: 262 | B263: economy.segment | C263: alex | D263: golf | E263: segment ending 2023-11-19 07:43 | G263: l/100km | H263: =IFERROR(ROUND(INDEX(fillups!$N$2:$N$596,MATCH("golf|2023-11-19 07:43",fillups!$O$2:$O$596,0)),2),"—") | I263: spreadsheet | K263: example formula (Claude): check it, or replace it with your own
A264: 263 | B264: economy.segment | C264: alex | D264: golf | E264: segment ending 2023-11-27 17:53 | G264: l/100km | H264: =IFERROR(ROUND(INDEX(fillups!$N$2:$N$596,MATCH("golf|2023-11-27 17:53",fillups!$O$2:$O$596,0)),2),"—") | I264: spreadsheet | K264: example formula (Claude): check it, or replace it with your own
A265: 264 | B265: economy.segment | C265: alex | D265: golf | E265: segment ending 2023-12-04 15:52 | G265: l/100km | H265: =IFERROR(ROUND(INDEX(fillups!$N$2:$N$596,MATCH("golf|2023-12-04 15:52",fillups!$O$2:$O$596,0)),2),"—") | I265: spreadsheet | K265: example formula (Claude): check it, or replace it with your own
A266: 265 | B266: economy.segment | C266: alex | D266: golf | E266: segment ending 2023-12-15 07:18 | G266: l/100km | H266: =IFERROR(ROUND(INDEX(fillups!$N$2:$N$596,MATCH("golf|2023-12-15 07:18",fillups!$O$2:$O$596,0)),2),"—") | I266: spreadsheet | K266: example formula (Claude): check it, or replace it with your own
A267: 266 | B267: economy.segment | C267: alex | D267: golf | E267: segment ending 2023-12-23 17:35 | G267: l/100km | H267: =IFERROR(ROUND(INDEX(fillups!$N$2:$N$596,MATCH("golf|2023-12-23 17:35",fillups!$O$2:$O$596,0)),2),"—") | I267: spreadsheet | K267: example formula (Claude): check it, or replace it with your own
A268: 267 | B268: economy.segment | C268: alex | D268: golf | E268: segment ending 2024-01-08 12:01 | G268: l/100km | H268: =IFERROR(ROUND(INDEX(fillups!$N$2:$N$596,MATCH("golf|2024-01-08 12:01",fillups!$O$2:$O$596,0)),2),"—") | I268: spreadsheet | K268: example formula (Claude): check it, or replace it with your own
A269: 268 | B269: economy.segment | C269: alex | D269: golf | E269: segment ending 2024-01-15 13:21 | G269: l/100km | H269: =IFERROR(ROUND(INDEX(fillups!$N$2:$N$596,MATCH("golf|2024-01-15 13:21",fillups!$O$2:$O$596,0)),2),"—") | I269: spreadsheet | K269: example formula (Claude): check it, or replace it with your own
A270: 269 | B270: economy.segment | C270: alex | D270: golf | E270: segment ending 2024-01-29 10:56 | G270: l/100km | H270: =IFERROR(ROUND(INDEX(fillups!$N$2:$N$596,MATCH("golf|2024-01-29 10:56",fillups!$O$2:$O$596,0)),2),"—") | I270: spreadsheet | K270: example formula (Claude): check it, or replace it with your own
A271: 270 | B271: economy.segment | C271: alex | D271: golf | E271: segment ending 2024-02-08 13:51 | G271: l/100km | H271: =IFERROR(ROUND(INDEX(fillups!$N$2:$N$596,MATCH("golf|2024-02-08 13:51",fillups!$O$2:$O$596,0)),2),"—") | I271: spreadsheet | K271: example formula (Claude): check it, or replace it with your own
A272: 271 | B272: economy.segment | C272: alex | D272: golf | E272: segment ending 2024-02-17 15:57 | G272: l/100km | H272: =IFERROR(ROUND(INDEX(fillups!$N$2:$N$596,MATCH("golf|2024-02-17 15:57",fillups!$O$2:$O$596,0)),2),"—") | I272: spreadsheet | K272: example formula (Claude): check it, or replace it with your own
A273: 272 | B273: economy.segment | C273: alex | D273: golf | E273: segment ending 2024-02-24 13:26 | G273: l/100km | H273: =IFERROR(ROUND(INDEX(fillups!$N$2:$N$596,MATCH("golf|2024-02-24 13:26",fillups!$O$2:$O$596,0)),2),"—") | I273: spreadsheet | K273: example formula (Claude): check it, or replace it with your own
A274: 273 | B274: economy.segment | C274: alex | D274: golf | E274: segment ending 2024-03-06 08:41 | G274: l/100km | H274: =IFERROR(ROUND(INDEX(fillups!$N$2:$N$596,MATCH("golf|2024-03-06 08:41",fillups!$O$2:$O$596,0)),2),"—") | I274: spreadsheet | K274: example formula (Claude): check it, or replace it with your own
A275: 274 | B275: economy.segment | C275: alex | D275: golf | E275: segment ending 2024-03-17 17:36 | G275: l/100km | H275: =IFERROR(ROUND(INDEX(fillups!$N$2:$N$596,MATCH("golf|2024-03-17 17:36",fillups!$O$2:$O$596,0)),2),"—") | I275: spreadsheet | K275: example formula (Claude): check it, or replace it with your own
A276: 275 | B276: economy.segment | C276: alex | D276: golf | E276: segment ending 2024-03-23 11:40 | G276: l/100km | H276: =IFERROR(ROUND(INDEX(fillups!$N$2:$N$596,MATCH("golf|2024-03-23 11:40",fillups!$O$2:$O$596,0)),2),"—") | I276: spreadsheet | K276: example formula (Claude): check it, or replace it with your own
A277: 276 | B277: economy.segment | C277: alex | D277: golf | E277: segment ending 2024-04-02 15:17 | G277: l/100km | H277: =IFERROR(ROUND(INDEX(fillups!$N$2:$N$596,MATCH("golf|2024-04-02 15:17",fillups!$O$2:$O$596,0)),2),"—") | I277: spreadsheet | K277: example formula (Claude): check it, or replace it with your own
A278: 277 | B278: economy.segment | C278: alex | D278: golf | E278: segment ending 2024-04-14 19:16 | G278: l/100km | H278: =IFERROR(ROUND(INDEX(fillups!$N$2:$N$596,MATCH("golf|2024-04-14 19:16",fillups!$O$2:$O$596,0)),2),"—") | I278: spreadsheet | K278: example formula (Claude): check it, or replace it with your own
A279: 278 | B279: economy.segment | C279: alex | D279: golf | E279: segment ending 2024-04-22 12:27 | G279: l/100km | H279: =IFERROR(ROUND(INDEX(fillups!$N$2:$N$596,MATCH("golf|2024-04-22 12:27",fillups!$O$2:$O$596,0)),2),"—") | I279: spreadsheet | K279: example formula (Claude): check it, or replace it with your own
A280: 279 | B280: economy.segment | C280: alex | D280: golf | E280: segment ending 2024-05-02 11:28 | G280: l/100km | H280: =IFERROR(ROUND(INDEX(fillups!$N$2:$N$596,MATCH("golf|2024-05-02 11:28",fillups!$O$2:$O$596,0)),2),"—") | I280: spreadsheet | K280: example formula (Claude): check it, or replace it with your own
A281: 280 | B281: economy.segment | C281: alex | D281: golf | E281: segment ending 2024-05-12 19:45 | G281: l/100km | H281: =IFERROR(ROUND(INDEX(fillups!$N$2:$N$596,MATCH("golf|2024-05-12 19:45",fillups!$O$2:$O$596,0)),2),"—") | I281: spreadsheet | K281: example formula (Claude): check it, or replace it with your own
A282: 281 | B282: economy.segment | C282: alex | D282: golf | E282: segment ending 2024-05-23 16:21 | G282: l/100km | H282: =IFERROR(ROUND(INDEX(fillups!$N$2:$N$596,MATCH("golf|2024-05-23 16:21",fillups!$O$2:$O$596,0)),2),"—") | I282: spreadsheet | K282: example formula (Claude): check it, or replace it with your own
A283: 282 | B283: economy.segment | C283: alex | D283: golf | E283: segment ending 2024-06-03 19:17 | G283: l/100km | H283: =IFERROR(ROUND(INDEX(fillups!$N$2:$N$596,MATCH("golf|2024-06-03 19:17",fillups!$O$2:$O$596,0)),2),"—") | I283: spreadsheet | K283: example formula (Claude): check it, or replace it with your own
A284: 283 | B284: economy.segment | C284: alex | D284: golf | E284: segment ending 2024-06-11 08:24 | G284: l/100km | H284: =IFERROR(ROUND(INDEX(fillups!$N$2:$N$596,MATCH("golf|2024-06-11 08:24",fillups!$O$2:$O$596,0)),2),"—") | I284: spreadsheet | K284: example formula (Claude): check it, or replace it with your own
A285: 284 | B285: economy.segment | C285: alex | D285: golf | E285: segment ending 2024-06-18 19:01 | G285: l/100km | H285: =IFERROR(ROUND(INDEX(fillups!$N$2:$N$596,MATCH("golf|2024-06-18 19:01",fillups!$O$2:$O$596,0)),2),"—") | I285: spreadsheet | K285: example formula (Claude): check it, or replace it with your own
A286: 285 | B286: economy.segment | C286: alex | D286: golf | E286: segment ending 2024-06-30 09:07 | G286: l/100km | H286: =IFERROR(ROUND(INDEX(fillups!$N$2:$N$596,MATCH("golf|2024-06-30 09:07",fillups!$O$2:$O$596,0)),2),"—") | I286: spreadsheet | K286: example formula (Claude): check it, or replace it with your own
A287: 286 | B287: economy.segment | C287: alex | D287: golf | E287: segment ending 2024-07-12 19:17 | G287: l/100km | H287: =IFERROR(ROUND(INDEX(fillups!$N$2:$N$596,MATCH("golf|2024-07-12 19:17",fillups!$O$2:$O$596,0)),2),"—") | I287: spreadsheet | K287: example formula (Claude): check it, or replace it with your own
A288: 287 | B288: economy.segment | C288: alex | D288: golf | E288: segment ending 2024-07-26 13:54 | G288: l/100km | H288: =IFERROR(ROUND(INDEX(fillups!$N$2:$N$596,MATCH("golf|2024-07-26 13:54",fillups!$O$2:$O$596,0)),2),"—") | I288: spreadsheet | K288: example formula (Claude): check it, or replace it with your own
A289: 288 | B289: economy.segment | C289: alex | D289: golf | E289: segment ending 2024-08-03 12:26 | G289: l/100km | H289: =IFERROR(ROUND(INDEX(fillups!$N$2:$N$596,MATCH("golf|2024-08-03 12:26",fillups!$O$2:$O$596,0)),2),"—") | I289: spreadsheet | K289: example formula (Claude): check it, or replace it with your own
A290: 289 | B290: economy.segment | C290: alex | D290: golf | E290: segment ending 2024-08-12 14:37 | G290: l/100km | H290: =IFERROR(ROUND(INDEX(fillups!$N$2:$N$596,MATCH("golf|2024-08-12 14:37",fillups!$O$2:$O$596,0)),2),"—") | I290: spreadsheet | K290: example formula (Claude): check it, or replace it with your own
A291: 290 | B291: economy.segment | C291: alex | D291: golf | E291: segment ending 2024-08-22 20:54 | G291: l/100km | H291: =IFERROR(ROUND(INDEX(fillups!$N$2:$N$596,MATCH("golf|2024-08-22 20:54",fillups!$O$2:$O$596,0)),2),"—") | I291: spreadsheet | K291: example formula (Claude): check it, or replace it with your own
A292: 291 | B292: economy.segment | C292: alex | D292: golf | E292: segment ending 2024-08-31 14:59 | G292: l/100km | H292: =IFERROR(ROUND(INDEX(fillups!$N$2:$N$596,MATCH("golf|2024-08-31 14:59",fillups!$O$2:$O$596,0)),2),"—") | I292: spreadsheet | K292: example formula (Claude): check it, or replace it with your own
A293: 292 | B293: economy.segment | C293: alex | D293: golf | E293: segment ending 2024-09-10 14:35 | G293: l/100km | H293: =IFERROR(ROUND(INDEX(fillups!$N$2:$N$596,MATCH("golf|2024-09-10 14:35",fillups!$O$2:$O$596,0)),2),"—") | I293: spreadsheet | K293: example formula (Claude): check it, or replace it with your own
A294: 293 | B294: economy.segment | C294: alex | D294: golf | E294: segment ending 2024-09-18 11:30 | G294: l/100km | H294: =IFERROR(ROUND(INDEX(fillups!$N$2:$N$596,MATCH("golf|2024-09-18 11:30",fillups!$O$2:$O$596,0)),2),"—") | I294: spreadsheet | K294: example formula (Claude): check it, or replace it with your own
A295: 294 | B295: economy.segment | C295: alex | D295: golf | E295: segment ending 2024-10-01 15:47 | G295: l/100km | H295: =IFERROR(ROUND(INDEX(fillups!$N$2:$N$596,MATCH("golf|2024-10-01 15:47",fillups!$O$2:$O$596,0)),2),"—") | I295: spreadsheet | K295: example formula (Claude): check it, or replace it with your own
A296: 295 | B296: economy.segment | C296: alex | D296: golf | E296: segment ending 2024-10-10 20:09 | G296: l/100km | H296: =IFERROR(ROUND(INDEX(fillups!$N$2:$N$596,MATCH("golf|2024-10-10 20:09",fillups!$O$2:$O$596,0)),2),"—") | I296: spreadsheet | K296: example formula (Claude): check it, or replace it with your own
A297: 296 | B297: economy.segment | C297: alex | D297: golf | E297: segment ending 2024-10-21 15:15 | G297: l/100km | H297: =IFERROR(ROUND(INDEX(fillups!$N$2:$N$596,MATCH("golf|2024-10-21 15:15",fillups!$O$2:$O$596,0)),2),"—") | I297: spreadsheet | K297: example formula (Claude): check it, or replace it with your own
A298: 297 | B298: economy.segment | C298: alex | D298: golf | E298: segment ending 2024-10-30 12:51 | G298: l/100km | H298: =IFERROR(ROUND(INDEX(fillups!$N$2:$N$596,MATCH("golf|2024-10-30 12:51",fillups!$O$2:$O$596,0)),2),"—") | I298: spreadsheet | K298: example formula (Claude): check it, or replace it with your own
A299: 298 | B299: economy.segment | C299: alex | D299: golf | E299: segment ending 2024-11-08 13:57 | G299: l/100km | H299: =IFERROR(ROUND(INDEX(fillups!$N$2:$N$596,MATCH("golf|2024-11-08 13:57",fillups!$O$2:$O$596,0)),2),"—") | I299: spreadsheet | K299: example formula (Claude): check it, or replace it with your own
A300: 299 | B300: economy.segment | C300: alex | D300: golf | E300: segment ending 2024-11-17 12:30 | G300: l/100km | H300: =IFERROR(ROUND(INDEX(fillups!$N$2:$N$596,MATCH("golf|2024-11-17 12:30",fillups!$O$2:$O$596,0)),2),"—") | I300: spreadsheet | K300: example formula (Claude): check it, or replace it with your own
A301: 300 | B301: economy.segment | C301: alex | D301: golf | E301: segment ending 2024-11-26 15:17 | G301: l/100km | H301: =IFERROR(ROUND(INDEX(fillups!$N$2:$N$596,MATCH("golf|2024-11-26 15:17",fillups!$O$2:$O$596,0)),2),"—") | I301: spreadsheet | K301: example formula (Claude): check it, or replace it with your own
A302: 301 | B302: economy.segment | C302: alex | D302: golf | E302: segment ending 2024-12-03 18:19 | G302: l/100km | H302: =IFERROR(ROUND(INDEX(fillups!$N$2:$N$596,MATCH("golf|2024-12-03 18:19",fillups!$O$2:$O$596,0)),2),"—") | I302: spreadsheet | K302: example formula (Claude): check it, or replace it with your own
A303: 302 | B303: economy.segment | C303: alex | D303: golf | E303: segment ending 2024-12-14 11:45 | G303: l/100km | H303: =IFERROR(ROUND(INDEX(fillups!$N$2:$N$596,MATCH("golf|2024-12-14 11:45",fillups!$O$2:$O$596,0)),2),"—") | I303: spreadsheet | K303: example formula (Claude): check it, or replace it with your own
A304: 303 | B304: economy.segment | C304: alex | D304: golf | E304: segment ending 2024-12-22 19:13 | G304: l/100km | H304: =IFERROR(ROUND(INDEX(fillups!$N$2:$N$596,MATCH("golf|2024-12-22 19:13",fillups!$O$2:$O$596,0)),2),"—") | I304: spreadsheet | K304: example formula (Claude): check it, or replace it with your own
A305: 304 | B305: economy.segment | C305: alex | D305: golf | E305: segment ending 2024-12-30 16:48 | G305: l/100km | H305: =IFERROR(ROUND(INDEX(fillups!$N$2:$N$596,MATCH("golf|2024-12-30 16:48",fillups!$O$2:$O$596,0)),2),"—") | I305: spreadsheet | K305: example formula (Claude): check it, or replace it with your own
A306: 305 | B306: economy.segment | C306: alex | D306: golf | E306: segment ending 2025-01-10 20:39 | G306: l/100km | H306: =IFERROR(ROUND(INDEX(fillups!$N$2:$N$596,MATCH("golf|2025-01-10 20:39",fillups!$O$2:$O$596,0)),2),"—") | I306: spreadsheet | K306: example formula (Claude): check it, or replace it with your own
A307: 306 | B307: economy.segment | C307: alex | D307: golf | E307: segment ending 2025-01-25 14:54 | G307: l/100km | H307: =IFERROR(ROUND(INDEX(fillups!$N$2:$N$596,MATCH("golf|2025-01-25 14:54",fillups!$O$2:$O$596,0)),2),"—") | I307: spreadsheet | K307: example formula (Claude): check it, or replace it with your own
A308: 307 | B308: economy.segment | C308: alex | D308: golf | E308: segment ending 2025-02-06 20:03 | G308: l/100km | H308: =IFERROR(ROUND(INDEX(fillups!$N$2:$N$596,MATCH("golf|2025-02-06 20:03",fillups!$O$2:$O$596,0)),2),"—") | I308: spreadsheet | K308: example formula (Claude): check it, or replace it with your own
A309: 308 | B309: economy.segment | C309: alex | D309: golf | E309: segment ending 2025-02-18 10:39 | G309: l/100km | H309: =IFERROR(ROUND(INDEX(fillups!$N$2:$N$596,MATCH("golf|2025-02-18 10:39",fillups!$O$2:$O$596,0)),2),"—") | I309: spreadsheet | K309: example formula (Claude): check it, or replace it with your own
A310: 309 | B310: economy.segment | C310: alex | D310: golf | E310: segment ending 2025-03-01 12:40 | G310: l/100km | H310: =IFERROR(ROUND(INDEX(fillups!$N$2:$N$596,MATCH("golf|2025-03-01 12:40",fillups!$O$2:$O$596,0)),2),"—") | I310: spreadsheet | K310: example formula (Claude): check it, or replace it with your own
A311: 310 | B311: economy.segment | C311: alex | D311: golf | E311: segment ending 2025-03-15 08:12 | G311: l/100km | H311: =IFERROR(ROUND(INDEX(fillups!$N$2:$N$596,MATCH("golf|2025-03-15 08:12",fillups!$O$2:$O$596,0)),2),"—") | I311: spreadsheet | K311: example formula (Claude): check it, or replace it with your own
A312: 311 | B312: economy.segment | C312: alex | D312: golf | E312: segment ending 2025-03-27 20:00 | G312: l/100km | H312: =IFERROR(ROUND(INDEX(fillups!$N$2:$N$596,MATCH("golf|2025-03-27 20:00",fillups!$O$2:$O$596,0)),2),"—") | I312: spreadsheet | K312: example formula (Claude): check it, or replace it with your own
A313: 312 | B313: economy.segment | C313: alex | D313: golf | E313: segment ending 2025-04-06 14:54 | G313: l/100km | H313: =IFERROR(ROUND(INDEX(fillups!$N$2:$N$596,MATCH("golf|2025-04-06 14:54",fillups!$O$2:$O$596,0)),2),"—") | I313: spreadsheet | K313: example formula (Claude): check it, or replace it with your own
A314: 313 | B314: economy.segment | C314: alex | D314: golf | E314: segment ending 2025-04-15 17:38 | G314: l/100km | H314: =IFERROR(ROUND(INDEX(fillups!$N$2:$N$596,MATCH("golf|2025-04-15 17:38",fillups!$O$2:$O$596,0)),2),"—") | I314: spreadsheet | K314: example formula (Claude): check it, or replace it with your own
A315: 314 | B315: economy.segment | C315: alex | D315: golf | E315: segment ending 2025-04-24 15:55 | G315: l/100km | H315: =IFERROR(ROUND(INDEX(fillups!$N$2:$N$596,MATCH("golf|2025-04-24 15:55",fillups!$O$2:$O$596,0)),2),"—") | I315: spreadsheet | K315: example formula (Claude): check it, or replace it with your own
A316: 315 | B316: economy.segment | C316: alex | D316: golf | E316: segment ending 2025-05-05 16:00 | G316: l/100km | H316: =IFERROR(ROUND(INDEX(fillups!$N$2:$N$596,MATCH("golf|2025-05-05 16:00",fillups!$O$2:$O$596,0)),2),"—") | I316: spreadsheet | K316: example formula (Claude): check it, or replace it with your own
A317: 316 | B317: economy.segment | C317: alex | D317: golf | E317: segment ending 2025-05-16 07:23 | G317: l/100km | H317: =IFERROR(ROUND(INDEX(fillups!$N$2:$N$596,MATCH("golf|2025-05-16 07:23",fillups!$O$2:$O$596,0)),2),"—") | I317: spreadsheet | K317: example formula (Claude): check it, or replace it with your own
A318: 317 | B318: economy.segment | C318: alex | D318: golf | E318: segment ending 2025-05-25 11:30 | G318: l/100km | H318: =IFERROR(ROUND(INDEX(fillups!$N$2:$N$596,MATCH("golf|2025-05-25 11:30",fillups!$O$2:$O$596,0)),2),"—") | I318: spreadsheet | K318: example formula (Claude): check it, or replace it with your own
A319: 318 | B319: economy.segment | C319: alex | D319: golf | E319: segment ending 2025-06-02 20:10 | G319: l/100km | H319: =IFERROR(ROUND(INDEX(fillups!$N$2:$N$596,MATCH("golf|2025-06-02 20:10",fillups!$O$2:$O$596,0)),2),"—") | I319: spreadsheet | K319: example formula (Claude): check it, or replace it with your own
...

Sheet vehicles
A1: vehicle | B1: owner | C1: type | D1: make | E1: model | F1: variant | G1: fuel_type | H1: registration | I1: currency | J1: first_registered_on | K1: purchase_date | L1: purchase_price | M1: sale_date | N1: sale_price
A2: corolla | B2: sam | C2: car | D2: Toyota | E2: Corolla | F2: 1.8 Hybrid Luna | G2: hybrid | H2: 211-D-48213 | I2: EUR | J2: 2021-02-11 | K2: 2023-11-04 | L2: 21400
A3: ev | B3: alex | C3: car | D3: Kia | E3: Niro EV | F3: 4 | G3: ev | H3: YC23 EVN | I3: GBP | J3: 2023-06-15 | K3: 2024-02-10 | L3: 27500
A4: focus | B4: alex | C4: car | D4: Ford | E4: Focus | F4: 1.5 TDCi Zetec | G4: diesel | H4: YK16 FCS | I4: GBP | J4: 2016-05-20 | K4: 2023-09-20 | L4: 6450 | M4: 2026-08-19 | N4: 3350
A5: golf | B5: alex | C5: car | D5: Volkswagen | E5: Golf | F5: 1.5 TSI Life | G5: petrol | H5: YH20 KLM | I5: GBP | J5: 2020-03-02 | K5: 2023-10-07 | L5: 17995

Sheet shares
A1: vehicle | B1: user | C1: level | D1: costs | E1: notify | F1: date
A2: corolla | B2: alex | C2: view | D2: yes | E2: yes | F2: 2023-11-04
A3: golf | B3: sam | C3: log | D3: no | E3: yes | F3: 2023-10-07

Sheet readings
A1: vehicle | B1: by | C1: at | D1: odometer_km | E1: note
A2: corolla | B2: sam | C2: 2023-11-04 14:30 | D2: 52700 | E2: Odometer when bought
A3: ev | B3: alex | C3: 2024-02-10 15:00 | D3: 6120 | E3: Odometer when bought
A4: focus | B4: alex | C4: 2023-09-20 11:00 | D4: 96300 | E4: Odometer when bought
A5: focus | B5: alex | C5: 2026-08-19 10:00 | D5: 136127.9 | E5: Odometer at sale
A6: golf | B6: alex | C6: 2023-10-07 12:00 | D6: 38412 | E6: Odometer when bought

Sheet fillups
A1: vehicle | B1: by | C1: at | D1: odometer_km | E1: fuel | F1: volume | G1: price_per_unit | H1: total_cost | I1: partial | J1: station | K1: prev_full_odometer | L1: volume_since_prev_full | M1: segment_km | N1: segment_per_100km | O1: key
A2: corolla | B2: sam | C2: 2023-11-21 16:25 | D2: 53412 | E2: petrol | F2: 18.38 | G2: 1.787 | H2: 32.85 | I2: yes | J2: Maxol Malahide | K2: ="" | L2: ="" | M2: =IF(AND(I2="no",K2<>""),D2-K2,"") | N2: =IF(M2="","",L2/M2*100) | O2: =A2&"|"&C2
A3: corolla | B3: sam | C3: 2023-11-30 11:45 | D3: 53820.3 | E3: petrol | F3: 35.554 | G3: 1.803 | H3: 64.1 | I3: no | J3: Applegreen Airside | K3: =IF(A3<>A2,"",IF(I2="no",D2,K2)) | L3: =IF(OR(A3<>A2,K3=""),"",IF(I2="no",F3,L2+F3)) | M3: =IF(AND(I3="no",K3<>""),D3-K3,"") | N3: =IF(M3="","",L3/M3*100) | O3: =A3&"|"&C3
A4: corolla | B4: sam | C4: 2023-12-15 15:28 | D4: 54404 | E4: petrol | F4: 19.308 | G4: 1.792 | H4: 34.6 | I4: yes | J4: Circle K Swords | K4: =IF(A4<>A3,"",IF(I3="no",D3,K3)) | L4: =IF(OR(A4<>A3,K4=""),"",IF(I3="no",F4,L3+F4)) | M4: =IF(AND(I4="no",K4<>""),D4-K4,"") | N4: =IF(M4="","",L4/M4*100) | O4: =A4&"|"&C4
A5: corolla | B5: sam | C5: 2023-12-23 08:13 | D5: 54796.4 | E5: petrol | F5: 26.549 | G5: 1.797 | H5: 47.71 | I5: no | J5: Applegreen Airside | K5: =IF(A5<>A4,"",IF(I4="no",D4,K4)) | L5: =IF(OR(A5<>A4,K5=""),"",IF(I4="no",F5,L4+F5)) | M5: =IF(AND(I5="no",K5<>""),D5-K5,"") | N5: =IF(M5="","",L5/M5*100) | O5: =A5&"|"&C5
A6: corolla | B6: sam | C6: 2024-01-08 16:41 | D6: 55520 | E6: petrol | F6: 33.502 | G6: 1.796 | H6: 60.17 | I6: no | J6: Applegreen Airside | K6: =IF(A6<>A5,"",IF(I5="no",D5,K5)) | L6: =IF(OR(A6<>A5,K6=""),"",IF(I5="no",F6,L5+F6)) | M6: =IF(AND(I6="no",K6<>""),D6-K6,"") | N6: =IF(M6="","",L6/M6*100) | O6: =A6&"|"&C6
A7: corolla | B7: sam | C7: 2024-01-25 20:05 | D7: 56327.9 | E7: petrol | F7: 37.044 | G7: 1.8 | H7: 66.68 | I7: no | J7: Applegreen Airside | K7: =IF(A7<>A6,"",IF(I6="no",D6,K6)) | L7: =IF(OR(A7<>A6,K7=""),"",IF(I6="no",F7,L6+F7)) | M7: =IF(AND(I7="no",K7<>""),D7-K7,"") | N7: =IF(M7="","",L7/M7*100) | O7: =A7&"|"&C7
A8: corolla | B8: sam | C8: 2024-02-12 10:01 | D8: 57075.5 | E8: petrol | F8: 36.487 | G8: 1.798 | H8: 65.6 | I8: no | J8: Applegreen Airside | K8: =IF(A8<>A7,"",IF(I7="no",D7,K7)) | L8: =IF(OR(A8<>A7,K8=""),"",IF(I7="no",F8,L7+F8)) | M8: =IF(AND(I8="no",K8<>""),D8-K8,"") | N8: =IF(M8="","",L8/M8*100) | O8: =A8&"|"&C8
A9: corolla | B9: sam | C9: 2024-02-27 11:38 | D9: 57754.9 | E9: petrol | F9: 31.706 | G9: 1.798 | H9: 57.01 | I9: no | J9: Maxol Malahide | K9: =IF(A9<>A8,"",IF(I8="no",D8,K8)) | L9: =IF(OR(A9<>A8,K9=""),"",IF(I8="no",F9,L8+F9)) | M9: =IF(AND(I9="no",K9<>""),D9-K9,"") | N9: =IF(M9="","",L9/M9*100) | O9: =A9&"|"&C9
A10: corolla | B10: sam | C10: 2024-03-13 15:05 | D10: 58408 | E10: petrol | F10: 30.338 | G10: 1.774 | H10: 53.82 | I10: no | J10: Applegreen Airside | K10: =IF(A10<>A9,"",IF(I9="no",D9,K9)) | L10: =IF(OR(A10<>A9,K10=""),"",IF(I9="no",F10,L9+F10)) | M10: =IF(AND(I10="no",K10<>""),D10-K10,"") | N10: =IF(M10="","",L10/M10*100) | O10: =A10&"|"&C10
A11: corolla | B11: sam | C11: 2024-03-27 12:10 | D11: 59066.1 | E11: petrol | F11: 30.714 | G11: 1.777 | H11: 54.58 | I11: no | J11: Circle K Swords | K11: =IF(A11<>A10,"",IF(I10="no",D10,K10)) | L11: =IF(OR(A11<>A10,K11=""),"",IF(I10="no",F11,L10+F11)) | M11: =IF(AND(I11="no",K11<>""),D11-K11,"") | N11: =IF(M11="","",L11/M11*100) | O11: =A11&"|"&C11
A12: corolla | B12: sam | C12: 2024-03-31 23:30 | D12: 59283.1 | E12: petrol | F12: 8.345 | G12: 1.775 | H12: 14.81 | I12: no | J12: Applegreen Airside | K12: =IF(A12<>A11,"",IF(I11="no",D11,K11)) | L12: =IF(OR(A12<>A11,K12=""),"",IF(I11="no",F12,L11+F12)) | M12: =IF(AND(I12="no",K12<>""),D12-K12,"") | N12: =IF(M12="","",L12/M12*100) | O12: =A12&"|"&C12
A13: corolla | B13: sam | C13: 2024-04-14 08:43 | D13: 59984.8 | E13: petrol | F13: 33.846 | G13: 1.78 | H13: 60.25 | I13: no | J13: Applegreen Airside | K13: =IF(A13<>A12,"",IF(I12="no",D12,K12)) | L13: =IF(OR(A13<>A12,K13=""),"",IF(I12="no",F13,L12+F13)) | M13: =IF(AND(I13="no",K13<>""),D13-K13,"") | N13: =IF(M13="","",L13/M13*100) | O13: =A13&"|"&C13
A14: corolla | B14: sam | C14: 2024-04-28 17:53 | D14: 60545.1 | E14: petrol | F14: 16.665 | G14: 1.769 | H14: 29.48 | I14: yes | J14: Circle K Swords | K14: =IF(A14<>A13,"",IF(I13="no",D13,K13)) | L14: =IF(OR(A14<>A13,K14=""),"",IF(I13="no",F14,L13+F14)) | M14: =IF(AND(I14="no",K14<>""),D14-K14,"") | N14: =IF(M14="","",L14/M14*100) | O14: =A14&"|"&C14
... A596: golf | B596: alex | C596: 2026-09-11 14:35 | D596: 105360.8 | E596: petrol | F596: 42.65 | G596: 1.383 | H596: 58.98 | I596: no | J596: Tesco Birstall | K596: =IF(A596<>A595,"",IF(I595="no",D595,K595)) | L596: =IF(OR(A596<>A595,K596=""),"",IF(I595="no",F596,L595+F596)) | M596: =IF(AND(I596="no",K596<>""),D596-K596,"") | N596: =IF(M596="","",L596/M596*100) | O596: =A596&"|"&C596

Sheet expenses
A1: vehicle | B1: date | C1: category | D1: amount | E1: note
A2: corolla | B2: 2023-11-04 | C2: tax | D2: 190 | E2: Motor tax
A3: corolla | B3: 2023-11-10 | C3: parking | D3: 6.6 | E3: Parking
A4: corolla | B4: 2023-12-31 | C4: parking | D4: 3.3 | E4: Parking
A5: corolla | B5: 2024-01-30 | C5: parking | D5: 5.8 | E5: Parking
A6: corolla | B6: 2024-02-18 | C6: tolls | D6: 3.1 | E6: M50 eFlow
A7: corolla | B7: 2024-02-18 | C7: parking | D7: 8.8 | E7: Parking
A8: corolla | B8: 2024-03-31 | C8: parking | D8: 9.8 | E8: Parking
A9: corolla | B9: 2024-04-18 | C9: parking | D9: 4.3 | E9: Parking
A10: corolla | B10: 2024-05-25 | C10: parking | D10: 2.4 | E10: Parking
A11: corolla | B11: 2024-06-25 | C11: parking | D11: 9.7 | E11: Parking
A12: corolla | B12: 2024-07-19 | C12: parking | D12: 6.5 | E12: Parking
A13: corolla | B13: 2024-08-25 | C13: parking | D13: 8.9 | E13: Parking
... A157: golf | B157: 2026-09-03 | C157: parking | D157: 5.7 | E157: Parking

Sheet maintenance
A1: vehicle | B1: date | C1: category | D1: title | E1: cost | F1: odometer_km | G1: vendor
A2: corolla | B2: 2024-11-12 | C2: service | D2: Toyota service | E2: 269 | F2: 69446.5 | G2: Toyota Swords
A3: corolla | B3: 2025-01-28 | C3: repair | D3: NCT pre-check: wiper blades, bulb | E3: 38.4 | F3: 72795.3 | G3: Toyota Swords
A4: corolla | B4: 2025-11-18 | C4: service | D4: Toyota service | E4: 284 | F4: 85698.9 | G4: Toyota Swords
A5: ev | B5: 2025-02-21 | C5: service | D5: Annual EV health check | E5: 149 | F5: 17641.2 | G5: Kia Leeds
A6: ev | B6: 2025-10-03 | C6: tyres | D6: Four tyres (EV rated) | E6: 736 | F6: 24590.1 | G6: Kwik Fit
A7: ev | B7: 2026-02-26 | C7: service | D7: Annual EV health check and cabin filter | E7: 189 | F7: 29047.2 | G7: Kia Leeds
A8: focus | B8: 2024-05-13 | C8: repair | D8: MOT advisory: rear brake hoses | E8: 96 | F8: 104994.4 | G8: Halfords
A9: focus | B9: 2024-08-02 | C9: service | D9: Interim service | E9: 179 | F9: 108020 | G9: Local garage
A10: focus | B10: 2024-12-02 | C10: bodywork | D10: Accident repair: rear bumper and tailgate | E10: 1430 | F10: 112667.9 | G10: Leeds Body Shop
A11: focus | B11: 2025-04-08 | C11: battery | D11: New battery | E11: 128.5 | F11: 117469.2 | G11: Halfords
A12: golf | B12: 2024-03-14 | C12: service | D12: Annual service | E12: 289 | F12: 48586.1 | G12: Leeds VW
A13: golf | B13: 2024-11-22 | C13: tyres | D13: Two front tyres | E13: 412.5 | F13: 64376.6 | G13: Kwik Fit
... A16: golf | B16: 2025-09-19 | C16: brakes | D16: Front discs and pads | E16: 286.4 | F16: 82891.6 | G16: Kwik Fit

Sheet documents
A1: vehicle | B1: type | C1: title | D1: provider | E1: start_on | F1: expiry_on | G1: cost
A2: corolla | B2: insurance | C2: Car insurance | D2: FBD | E2: 2023-11-04 | F2: 2024-11-03 | G2: 642
A3: corolla | B3: insurance | C3: Car insurance | D3: FBD | E3: 2024-11-04 | F3: 2025-11-03 | G3: 688.5
A4: corolla | B4: inspection | C4: NCT | D4: NCTS Northpoint | E4: 2025-02-03 | F4: 2027-02-02 | G4: 55
A5: corolla | B5: insurance | C5: Car insurance | D5: FBD | E5: 2025-11-04 | F5: 2026-11-03 | G5: 701.25
A6: ev | B6: insurance | C6: Car insurance | D6: Direct Line | E6: 2024-02-10 | F6: 2025-02-09 | G6: 804.2
A7: ev | B7: insurance | C7: Car insurance | D7: Direct Line | E7: 2025-02-10 | F7: 2026-02-09 | G7: 871.66
A8: ev | B8: insurance | C8: Car insurance | D8: Direct Line | E8: 2026-02-10 | F8: 2027-02-09 | G8: 845.03
A9: ev | B9: inspection | C9: First MOT | D9: Kwik Fit | E9: 2026-06-12 | F9: 2027-06-11 | G9: 54.85
A10: focus | B10: insurance | C10: Car insurance | D10: Aviva | E10: 2023-09-20 | F10: 2024-09-19 | G10: 455.7
A11: focus | B11: inspection | C11: MOT | D11: Halfords | E11: 2024-05-14 | F11: 2025-05-13 | G11: 54.85
A12: focus | B12: insurance | C12: Car insurance | D12: Aviva | E12: 2024-09-20 | F12: 2025-09-19 | G12: 518.22
A13: focus | B13: inspection | C13: MOT | D13: Halfords | E13: 2025-05-12 | F13: 2026-05-11 | G13: 54.85
... A20: golf | B20: insurance | C20: Car insurance | D20: Admiral | E20: 2025-10-07 | F20: 2026-10-06 | G20: 731.95

Sheet valuations
A1: vehicle | B1: valued_on | C1: amount | D1: source
A2: corolla | B2: 2025-11-01 | C2: 17200 | D2: Carzone guide
A3: ev | B3: 2025-02-10 | C3: 22000 | D3: Online guide
A4: ev | B4: 2026-02-10 | C4: 19250 | D4: Online guide
A5: focus | B5: 2023-09-20 | C5: 6200 | D5: Trade guide on the day of purchase
A6: focus | B6: 2024-09-20 | C6: 5300 | D6: Online guide
A7: focus | B7: 2025-05-01 | C7: 3900 | D7: Online guide
A8: focus | B8: 2026-03-01 | C8: 3150 | D8: Online guide
A9: golf | B9: 2024-04-10 | C9: 16100 | D9: Dealer part-exchange quote
A10: golf | B10: 2024-10-01 | C10: 14900 | D10: Online guide
A11: golf | B11: 2025-06-30 | C11: 13400 | D11: Online guide (stale by today)

Sheet schedules
A1: vehicle | B1: category | C1: title | D1: interval_km | E1: interval_months | F1: baseline_done_on | G1: baseline_done_km
A2: corolla | B2: service | C2: Toyota service | D2: 15000 | E2: 12 | F2: 2025-11-18 | G2: 85698.9
A3: ev | B3: service | C3: Annual EV health check | E3: 12 | F3: 2026-02-26 | G3: 29047.2
A4: golf | B4: service | C4: Annual service | D4: 24140 | E4: 12 | F4: 2025-03-20 | G4: 71684.2

Sheet incidents
A1: vehicle | B1: occurred_on | C1: type | D1: fault | E1: claim_status | F1: insurer | G1: excess | H1: payout | I1: updated_on | J1: status | K1: closed_on | L1: note
A2: focus | B2: 2024-11-08 | C2: collision | D2: not_at_fault | E2: settled | F2: Aviva | G2: 250 | H2: 1180 | I2: 2025-01-10 | J2: closed | K2: 2025-01-10 | L2: Rear-ended at lights; repair 2 Dec 2024 (maintenance)

Sheet finance
A1: vehicle | B1: agreement | C1: type | D1: lender | E1: started_on | F1: first_payment_on | G1: number_of_payments | H1: first_payment | I1: regular_payment | J1: final_payment | K1: final_payment_on | L1: cash_price | M1: customer_deposit | N1: dealer_contribution | O1: amount_of_credit | P1: apr | Q1: documentation_fee | R1: option_to_purchase_fee | S1: annual_mileage_allowance | T1: mileage_unit | U1: excess_mileage_charge | V1: start_odometer_km | W1: count_in_costs
A2: ev | B2: ev-hp | C2: hp | D2: Greenline Finance | E2: 2024-02-10 | F2: 2024-03-10 | G2: 48 | I2: 549.17 | L2: 27500 | M2: 4000 | N2: 0 | O2: 23500 | P2: 5.9 | T2: mi | W2: yes
A3: golf | B3: golf-pcp | C3: pcp | D3: Northway Motor Finance | E3: 2023-10-07 | F3: 2023-11-07 | G3: 36 | I3: 284.85 | J3: 7650 | K3: 2026-11-07 | L3: 17995 | M3: 2000 | N3: 500 | O3: 15495 | P3: 6.9 | R3: 10 | S3: 15000 | T3: mi | U3: 0.08 | V3: 38412 | W3: yes

Sheet finance_events
A1: vehicle | B1: agreement | C1: kind | D1: date | E1: due_on | F1: amount | G1: note
A2: ev | B2: ev-hp | C2: missed | E2: 2025-01-10 | G2: Direct debit failed
A3: ev | B3: ev-hp | C3: paid_late | D3: 2025-01-24 | E3: 2025-01-10 | G3: Paid by card
A4: golf | B4: golf-pcp | C4: settled | D4: 2026-05-15 | F4: 8812.62 | G4: Settled early: the lender's quote, balloon included

Sheet rate_sets
A1: user | B1: effective_from | C1: distance_unit | D1: currency | E1: car_rate | F1: car_threshold | G1: car_rate_after | H1: source
A2: alex | B2: 2023-04-06 | C2: mi | D2: GBP | E2: 0.45 | F2: 10000 | G2: 0.25 | H2: HMRC AMAP
A3: alex | B3: 2025-10-01 | C3: mi | D3: GBP | E3: 0.5 | F3: 10000 | G3: 0.3 | H3: Employer, from October 2025

Sheet trips
A1: vehicle | B1: user | C1: date | D1: from | E1: to | F1: return | G1: typed_miles_one_way | H1: distance_km | I1: business | J1: purpose | K1: tax_year | L1: miles
A2: golf | B2: alex | C2: 2023-10-11 | D2: Leeds | E2: Birmingham | F2: yes | G2: 118 | H2: 379.805 | I2: yes | J2: Client visit | K2: =IF(MID(C2,6,5)>="04-06",LEFT(C2,4)&"-"&RIGHT(LEFT(C2,4)+1,2),LEFT(C2,4)-1&"-"&RIGHT(LEFT(C2,4),2)) | L2: =H2/1.609344
A3: golf | B3: alex | C3: 2023-10-19 | D3: Leeds | E3: Birmingham | F3: yes | G3: 118 | H3: 379.805 | I3: yes | J3: Client visit | K3: =IF(MID(C3,6,5)>="04-06",LEFT(C3,4)&"-"&RIGHT(LEFT(C3,4)+1,2),LEFT(C3,4)-1&"-"&RIGHT(LEFT(C3,4),2)) | L3: =H3/1.609344
A4: golf | B4: alex | C4: 2023-10-25 | D4: Leeds | E4: Birmingham | F4: yes | G4: 118 | H4: 379.805 | I4: yes | J4: Client visit | K4: =IF(MID(C4,6,5)>="04-06",LEFT(C4,4)&"-"&RIGHT(LEFT(C4,4)+1,2),LEFT(C4,4)-1&"-"&RIGHT(LEFT(C4,4),2)) | L4: =H4/1.609344
A5: golf | B5: alex | C5: 2023-10-31 | D5: Leeds | E5: Birmingham | F5: yes | G5: 118 | H5: 379.805 | I5: yes | J5: Client visit | K5: =IF(MID(C5,6,5)>="04-06",LEFT(C5,4)&"-"&RIGHT(LEFT(C5,4)+1,2),LEFT(C5,4)-1&"-"&RIGHT(LEFT(C5,4),2)) | L5: =H5/1.609344
A6: golf | B6: alex | C6: 2023-11-10 | D6: Leeds | E6: Birmingham | F6: yes | G6: 118 | H6: 379.805 | I6: yes | J6: Client visit | K6: =IF(MID(C6,6,5)>="04-06",LEFT(C6,4)&"-"&RIGHT(LEFT(C6,4)+1,2),LEFT(C6,4)-1&"-"&RIGHT(LEFT(C6,4),2)) | L6: =H6/1.609344
A7: golf | B7: alex | C7: 2023-11-15 | D7: Leeds | E7: Birmingham | F7: yes | G7: 118 | H7: 379.805 | I7: yes | J7: Client visit | K7: =IF(MID(C7,6,5)>="04-06",LEFT(C7,4)&"-"&RIGHT(LEFT(C7,4)+1,2),LEFT(C7,4)-1&"-"&RIGHT(LEFT(C7,4),2)) | L7: =H7/1.609344
A8: golf | B8: alex | C8: 2023-11-23 | D8: Leeds | E8: Birmingham | F8: yes | G8: 118 | H8: 379.805 | I8: yes | J8: Client visit | K8: =IF(MID(C8,6,5)>="04-06",LEFT(C8,4)&"-"&RIGHT(LEFT(C8,4)+1,2),LEFT(C8,4)-1&"-"&RIGHT(LEFT(C8,4),2)) | L8: =H8/1.609344
A9: golf | B9: alex | C9: 2023-11-29 | D9: Leeds | E9: Birmingham | F9: yes | G9: 118 | H9: 379.805 | I9: yes | J9: Client visit | K9: =IF(MID(C9,6,5)>="04-06",LEFT(C9,4)&"-"&RIGHT(LEFT(C9,4)+1,2),LEFT(C9,4)-1&"-"&RIGHT(LEFT(C9,4),2)) | L9: =H9/1.609344
A10: golf | B10: alex | C10: 2023-12-05 | D10: Leeds | E10: Birmingham | F10: yes | G10: 118 | H10: 379.805 | I10: yes | J10: Client visit | K10: =IF(MID(C10,6,5)>="04-06",LEFT(C10,4)&"-"&RIGHT(LEFT(C10,4)+1,2),LEFT(C10,4)-1&"-"&RIGHT(LEFT(C10,4),2)) | L10: =H10/1.609344
A11: golf | B11: alex | C11: 2023-12-12 | D11: Leeds | E11: Birmingham | F11: yes | G11: 118 | H11: 379.805 | I11: yes | J11: Client visit | K11: =IF(MID(C11,6,5)>="04-06",LEFT(C11,4)&"-"&RIGHT(LEFT(C11,4)+1,2),LEFT(C11,4)-1&"-"&RIGHT(LEFT(C11,4),2)) | L11: =H11/1.609344
A12: golf | B12: alex | C12: 2023-12-19 | D12: Leeds | E12: Birmingham | F12: yes | G12: 118 | H12: 379.805 | I12: yes | J12: Client visit | K12: =IF(MID(C12,6,5)>="04-06",LEFT(C12,4)&"-"&RIGHT(LEFT(C12,4)+1,2),LEFT(C12,4)-1&"-"&RIGHT(LEFT(C12,4),2)) | L12: =H12/1.609344
A13: golf | B13: alex | C13: 2024-01-10 | D13: Leeds | E13: Birmingham | F13: yes | G13: 118 | H13: 379.805 | I13: yes | J13: Client visit | K13: =IF(MID(C13,6,5)>="04-06",LEFT(C13,4)&"-"&RIGHT(LEFT(C13,4)+1,2),LEFT(C13,4)-1&"-"&RIGHT(LEFT(C13,4),2)) | L13: =H13/1.609344
... A144: golf | B144: alex | C144: 2026-09-10 | D144: Leeds | E144: Birmingham | F144: yes | G144: 118 | H144: 379.805 | I144: yes | J144: Client visit | K144: =IF(MID(C144,6,5)>="04-06",LEFT(C144,4)&"-"&RIGHT(LEFT(C144,4)+1,2),LEFT(C144,4)-1&"-"&RIGHT(LEFT(C144,4),2)) | L144: =H144/1.609344
